{ "idkey": 0,
  "carro": {
    "data": {
      "modelo": "V8 Vantage S '15",
      "construtor": "Aston Martin",
      "pais": "Reino Unido",
      "categoria": "N400",
      "potencia_max_cv": 449,
      "potencia_max_rpm": 7100,
      "torque_max_mkgf": 51.4,
      "torque_max_rpm": 5000,
      "tracao": "FR",
      "aspiracao": "Aspirado",
      "cilindrada_cc": 4735,
      "comprimento_mm": 4385,
      "largura_mm": 2022,
      "altura_mm": 1260,
      "peso_kg": 1610,
      "ano": 2015
    },
    "desempenho": {
      "velocidade_max": 8.0,
      "aceleracao": 4.3,
      "freio": 2.2,
      "curva": 2.0,
      "estabilidade": 5.1
    },
    "status": {
      "distancia_percorrida": 11.3,
      "alteracao": 1,
      "numero_corridas": 0,
      "numero_vitorias": 0,
      "valor_real": 180000
    }
  }
}
